<?xml version='1.0' encoding='UTF-8' ?>
<header_vars>
<graphics_color>F6AE2C</graphics_color>
<animation_loop>no</animation_loop>

<header>
	<text_header_h1 x_pos="25" y_pos="100" size="23" letter_spacing="0" text_color="F6AE2C">Word of Warcraft</text_header_h1>
	<text_header_h2 x_pos="30" y_pos="125" size="15" letter_spacing="1.9" text_color="F6AE2C">YOUR OWN SLOGANS AND IMAGES</text_header_h2>	
	<image blur="no">images/flashimages/wow1.jpg</image>
</header>

<header>
	<text_header_h1 x_pos="25" y_pos="30" size="23" letter_spacing="0" text_color="F6AE2C">Word of Warcraft</text_header_h1>
	<text_header_h2 x_pos="30" y_pos="55" size="15" letter_spacing="1.9" text_color="F6AE2C">YOUR OWN SLOGANS AND IMAGES</text_header_h2>	
	<image blur="no">images/flashimages/wow2.jpg</image>
</header>
<header>
	<text_header_h1 x_pos="25" y_pos="50" size="23" letter_spacing="0" text_color="FFFFFF">Word of Warcraft</text_header_h1>
	<text_header_h2 x_pos="30" y_pos="75" size="15" letter_spacing="1.9" text_color="FFFFFF">YOUR OWN SLOGANS AND IMAGES</text_header_h2>	
	<image blur="no">images/flashimages/wow4.jpg</image>
</header>
<header>
	<text_header_h1 x_pos="25" y_pos="20" size="23" letter_spacing="7" text_color="F6AE2C">Word of Warcraft</text_header_h1>
	<text_header_h2 x_pos="30" y_pos="45" size="15" letter_spacing="1.3" text_color="F6AE2C">YOUR OWN SLOGANS AND IMAGES</text_header_h2>	
	<image blur="no">images/flashimages/wow3.jpg</image>
</header>
<music_file loop="yes" music_control="yes" play_music="yes">sounds/music.mp3</music_file>
<play_transition_sound_file>yes</play_transition_sound_file>
<display_preload graphic_color="F6AE2C">yes</display_preload>
<replay display="yes" x_pos="840" y_pos="480" size="8" letter_spacing="1" bgd_color="FFFFFF" text_color="000000"> REPLAY</replay>
</header_vars>